Workbook
Name Slicer_Category: #N/A
Name Slicer_Channel: #N/A
Name Slicer_City: #N/A
Name Slicer_Order_Year: #N/A

Sheet README
A1: Field | B1: Details
A2: Project | B2: Retail Sales Analysis — Excel
A3: Dataset size | B3: 1205
A4: Objective | B4: Clean retail sales data and build KPI/Pivot analysis.
A5: Intentional data issues | B5: 5 duplicate rows; some blank/lowercase City values; trailing spaces in Category.
A6: Suggested analysis | B6: Revenue, profit, margin, category/city trends, returns, monthly trend, top products.
A7: Portfolio disclosure | B7: This project uses synthetic data created for learning and portfolio purposes.
A8: Tip | B8: Keep the RAW data unchanged. Clean/analyze in a separate sheet, SQL table, Power Query, or Python notebook.

Sheet Retail_Raw
A1: Order_ID | B1: Order_Date | C1: Customer_ID | D1: City | E1: Category | F1: Product | G1: Quantity | H1: Unit_Price | I1: Discount_Pct | J1: Sales | K1: Cost | L1: Profit | M1: Channel | N1: Payment_Mode | O1: Returned
A2: R00001 | B2: 45690 | C2: C0474 | D2: Jaipur | E2: Fashion | F2: T-Shirt | G2: 2 | H2: 5217.86 | I2: 0.1 | J2: 9392.15 | K2: 7880.02 | L2: 1512.13 | M2: Online | N2: Cash | O2: Yes
A3: R00002 | B3: 45835 | C3: C0214 | D3: Kolkata | E3: Electronics | F3: Headphones | G3: 2 | H3: 5082.03 | I3: 0.15 | J3: 8639.45 | K3: 4816.51 | L3: 3822.94 | M3: Online | N3: Card | O3: No
A4: R00003 | B4: 46014 | C4: C0519 | D4: Delhi | E4: Home | F4: Bottle | G4: 6 | H4: 2053.18 | I4: 0.1 | J4: 11087.17 | K4: 6103.16 | L4: 4984.01 | M4: Online | N4: Card | O4: No
A5: R00004 | B5: 46028 | C5: C0332 | D5: Hyderabad | E5: Electronics | F5: Power Bank | G5: 4 | H5: 4983.19 | I5: 0.2 | J5: 15946.21 | K5: 12246.04 | L5: 3700.17 | M5: Online | N5: Card | O5: No
A6: R00005 | B6: 46207 | C6: C0017 | D6: Noida | E6: Electronics | F6: Power Bank | G6: 5 | H6: 2051.83 | I6: 0.2 | J6: 8207.32 | K6: 6877.01 | L6: 1330.31 | M6: Store | N6: Card | O6: No
A7: R00006 | B7: 45757 | C7: C0164 | D7: Pune | E7: Beauty | F7: Face Wash | G7: 5 | H7: 4206.56 | I7: 0 | J7: 21032.8 | K7: 16501.65 | L7: 4531.15 | M7: Store | N7: UPI | O7: No
A8: R00007 | B8: 45922 | C8: C0021 | D8: Mumbai | E8: Fashion | F8: Shoes | G8: 6 | H8: 1565.16 | I8: 0 | J8: 9390.96 | K8: 7467.25 | L8: 1923.71 | M8: Store | N8: UPI | O8: No
A9: R00008 | B9: 45803 | C9: C0493 | D9: Noida | E9: Home | F9: Lamp | G9: 5 | H9: 789.07 | I9: 0.1 | J9: 3550.82 | K9: 2348.82 | L9: 1202 | M9: Store | N9: Wallet | O9: Yes
A10: R00009 | B10: 45962 | C10: C0247 | D10: Bengaluru | E10: Beauty | F10: Face Wash | G10: 4 | H10: 5105.62 | I10: 0.1 | J10: 18380.23 | K10: 11088.51 | L10: 7291.72 | M10: Online | N10: UPI | O10: No
A11: R00010 | B11: 45676 | C11: C0491 | D11: Pune | E11: Fashion | F11: T-Shirt | G11: 1 | H11: 2653.55 | I11: 0.1 | J11: 2388.2 | K11: 1761.27 | L11: 626.93 | M11: Online | N11: Wallet | O11: Yes
A12: R00011 | B12: 45815 | C12: C0392 | D12: Noida | E12: Home | F12: Lamp | G12: 6 | H12: 4187.53 | I12: 0.05 | J12: 23868.92 | K12: 20074.74 | L12: 3794.18 | M12: Online | N12: Wallet | O12: No
A13: R00012 | B13: 45810 | C13: C0232 | D13: Noida | E13: Beauty | F13: Sunscreen | G13: 3 | H13: 4164.28 | I13: 0 | J13: 12492.84 | K13: 10464.94 | L13: 2027.9 | M13: Store | N13: Wallet | O13: No
... A411: R00410 | B411: 46209 | C411: C0316 | D411: Noida | E411: Home | F411: Lamp | G411: 6 | H411: 4695.74 | I411: 0.05 | J411: 26765.72 | K411: 20563.25 | L411: 6202.47 | M411: Online | N411: Card | O411: No
A412: R00411 | B412: 46083 | C412: C0231 | E412: Electronics | F412: Power Bank | G412: 1 | H412: 2506.2 | I412: 0.2 | J412: 2004.96 | K412: 1384.42 | L412: 620.54 | M412: Online | N412: Wallet | O412: No
A413: R00412 | B413: 46082 | C413: C0020 | D413: Hyderabad | E413: Fashion | F413: Backpack | G413: 3 | H413: 745.83 | I413: 0.05 | J413: 2125.62 | K413: 1243.98 | L413: 881.64 | M413: Store | N413: Wallet | O413: No
A414: R00413 | B414: 45669 | C414: C0494 | D414: Noida | E414: Fashion | F414: Jacket | G414: 4 | H414: 2363.22 | I414: 0.05 | J414: 8980.24 | K414: 6657.85 | L414: 2322.39 | M414: Store | N414: Cash | O414: No
A415: R00414 | B415: 45819 | C415: C0030 | D415: Delhi | E415: Home | F415: Bottle | G415: 6 | H415: 4252.4 | I415: 0 | J415: 25514.4 | K415: 20787.61 | L415: 4726.79 | M415: Store | N415: Card | O415: No
A416: R00415 | B416: 46087 | C416: C0330 | D416: Kolkata | E416: Beauty | F416: Perfume | G416: 6 | H416: 1795.81 | I416: 0 | J416: 10774.86 | K416: 5974.88 | L416: 4799.98 | M416: Online | N416: Card | O416: No
A417: R00416 | B417: 45843 | C417: C0248 | D417: Chennai | E417: Beauty | F417: Perfume | G417: 3 | H417: 5487.44 | I417: 0.15 | J417: 13992.97 | K417: 8709.8 | L417: 5283.17 | M417: Store | N417: Card | O417: No
A418: R00417 | B418: 45979 | C418: C0016 | D418: Noida | E418: Electronics | F418: Power Bank | G418: 4 | H418: 1784.88 | I418: 0.05 | J418: 6782.54 | K418: 4425.52 | L418: 2357.02 | M418: Online | N418: Wallet | O418: Yes
A419: R00418 | B419: 46138 | C419: C0104 | D419: Hyderabad | E419: Beauty | F419: Sunscreen | G419: 5 | H419: 1385.96 | I419: 0 | J419: 6929.8 | K419: 4860.97 | L419: 2068.83 | M419: Store | N419: UPI | O419: No
A420: R00419 | B420: 46154 | C420: C0425 | D420: Kolkata | E420: Fashion | F420: Shoes | G420: 1 | H420: 751.9 | I420: 0.15 | J420: 639.12 | K420: 422.85 | L420: 216.27 | M420: Online | N420: Cash | O420: No
A421: R00420 | B421: 45774 | C421: C0194 | D421: Gurugram | E421: Beauty | F421: Serum | G421: 5 | H421: 3632.24 | I421: 0 | J421: 18161.2 | K421: 12645.08 | L421: 5516.12 | M421: Online | N421: Cash | O421: No
A422: R00421 | B422: 46088 | C422: C0468 | D422: Noida | E422: Home | F422: Mixer | G422: 4 | H422: 1414.64 | I422: 0.1 | J422: 5092.7 | K422: 4168.44 | L422: 924.26 | M422: Store | N422: UPI | O422: No
A423: R00422 | B423: 45697 | C423: C0476 | D423: Delhi | E423: Beauty | F423: Face Wash | G423: 5 | H423: 5021.32 | I423: 0 | J423: 25106.6 | K423: 15976.89 | L423: 9129.71 | M423: Online | N423: Card | O423: No
A424: R00423 | B424: 46250 | C424: C0294 | D424: Mumbai | E424: Fashion | F424: Backpack | G424: 1 | H424: 5276.99 | I424: 0.2 | J424: 4221.59 | K424: 2423.65 | L424: 1797.94 | M424: Online | N424: Card | O424: No
A425: R00424 | B425: 45950 | C425: C0148 | E425: Home | F425: Bottle | G425: 2 | H425: 856.02 | I425: 0.15 | J425: 1455.23 | K425: 1065.2 | L425: 390.03 | M425: Online | N425: Card | O425: No
A426: R00425 | B426: 45952 | C426: C0043 | D426: Chennai | E426: Home | F426: Bottle | G426: 6 | H426: 5246.55 | I426: 0 | J426: 31479.3 | K426: 17716.9 | L426: 13762.4 | M426: Online | N426: Wallet | O426: Yes
A427: R00426 | B427: 45758 | C427: C0285 | D427: Mumbai | E427: Beauty | F427: Face Wash | G427: 3 | H427: 3991.91 | I427: 0.2 | J427: 9580.58 | K427: 6095.36 | L427: 3485.22 | M427: Online | N427: UPI | O427: Yes
A428: R00427 | B428: 45845 | C428: C0189 | D428: Delhi | E428: Beauty | F428: Serum | G428: 2 | H428: 3361.48 | I428: 0.15 | J428: 5714.52 | K428: 3250.65 | L428: 2463.87 | M428: Store | N428: UPI | O428: No
A429: R00428 | B429: 45954 | C429: C0261 | D429: Mumbai | E429: Fashion | F429: Jeans | G429: 6 | H429: 3226.75 | I429: 0 | J429: 19360.5 | K429: 10893.1 | L429: 8467.4 | M429: Online | N429: Cash | O429: No
A430: R00429 | B430: 45789 | C430: C0363 | D430: Chennai | E430: Home | F430: Bedsheet | G430: 4 | H430: 513.62 | I430: 0.05 | J430: 1951.76 | K430: 1142.94 | L430: 808.82 | M430: Store | N430: UPI | O430: No
A431: R00430 | B431: 46228 | C431: C0388 | D431: Pune | E431: Electronics | F431: Mouse | G431: 3 | H431: 5438.29 | I431: 0.15 | J431: 13867.64 | K431: 9000.63 | L431: 4867.01 | M431: Online | N431: Wallet | O431: Yes
A432: R00431 | B432: 45684 | C432: C0453 | D432: Kolkata | E432: Home | F432: Bedsheet | G432: 6 | H432: 4547.7 | I432: 0 | J432: 27286.2 | K432: 18622.55 | L432: 8663.65 | M432: Online | N432: Wallet | O432: Yes
A433: R00432 | B433: 45801 | C433: C0118 | D433: Mumbai | E433: Electronics | F433: Mouse | G433: 4 | H433: 583.48 | I433: 0 | J433: 2333.92 | K433: 1538.67 | L433: 795.25 | M433: Online | N433: Card | O433: No
A434: R00433 | B434: 46214 | C434: C0500 | D434: Jaipur | E434: Fashion | F434: Shoes | G434: 6 | H434: 5254.2 | I434: 0 | J434: 31525.2 | K434: 21334.09 | L434: 10191.11 | M434: Online | N434: Card | O434: No
A435: R00434 | B435: 46113 | C435: C0198 | D435: Pune | E435: Home | F435: Mixer | G435: 6 | H435: 3987.95 | I435: 0 | J435: 23927.7 | K435: 15740.47 | L435: 8187.23 | M435: Store | N435: UPI | O435: No
A436: R00435 | B436: 46197 | C436: C0046 | D436: Jaipur | E436: Fashion | F436: Backpack | G436: 3 | H436: 2376.97 | I436: 0.05 | J436: 6774.36 | K436: 5525.11 | L436: 1249.25 | M436: Store | N436: Card | O436: Yes
A437: R00436 | B437: 45914 | C437: C0181 | D437: Pune | E437: Fashion | F437: Jacket | G437: 6 | H437: 4093.7 | I437: 0.05 | J437: 23334.09 | K437: 16340.31 | L437: 6993.78 | M437: Online | N437: Cash | O437: Yes
... A737: R00736 | B737: 46235 | C737: C0128 | D737: Hyderabad | E737: Fashion | F737: Jeans | G737: 1 | H737: 1789.37 | I737: 0 | J737: 1789.37 | K737: 1148.31 | L737: 641.06 | M737: Store | N737: Cash | O737: Yes
A738: R00737 | B738: 45819 | C738: C0237 | E738: Home | F738: Bedsheet | G738: 2 | H738: 5397.99 | I738: 0 | J738: 10795.98 | K738: 7840.79 | L738: 2955.19 | M738: Online | N738: Card | O738: No
A739: R00738 | B739: 46137 | C739: C0434 | D739: Pune | E739: Beauty | F739: Perfume | G739: 4 | H739: 3999.67 | I739: 0.2 | J739: 12798.94 | K739: 10116.63 | L739: 2682.31 | M739: Store | N739: Cash | O739: No
A740: R00739 | B740: 45807 | C740: C0104 | D740: Gurugram | E740: Electronics | F740: Keyboard | G740: 2 | H740: 923.29 | I740: 0.1 | J740: 1661.92 | K740: 1374.57 | L740: 287.35 | M740: Store | N740: Cash | O740: Yes
A741: R00740 | B741: 46081 | C741: C0128 | D741: Mumbai | E741: Fashion | F741: Jeans | G741: 6 | H741: 199.23 | I741: 0.15 | J741: 1016.07 | K741: 636.88 | L741: 379.19 | M741: Online | N741: Wallet | O741: Yes
A742: R00741 | B742: 46118 | C742: C0357 | D742: Chennai | E742: Beauty | F742: Perfume | G742: 4 | H742: 1564.76 | I742: 0 | J742: 6259.04 | K742: 4497.8 | L742: 1761.24 | M742: Online | N742: Card | O742: No
A743: R00742 | B743: 45703 | C743: C0163 | D743: Bengaluru | E743: Home | F743: Lamp | G743: 6 | H743: 3696.09 | I743: 0.1 | J743: 19958.89 | K743: 12469.87 | L743: 7489.02 | M743: Store | N743: Cash | O743: No
A744: R00743 | B744: 45982 | C744: C0332 | D744: Hyderabad | E744: Electronics | F744: Smartwatch | G744: 6 | H744: 3311.98 | I744: 0.05 | J744: 18878.29 | K744: 12130.91 | L744: 6747.38 | M744: Online | N744: UPI | O744: Yes
A745: R00744 | B745: 45661 | C745: C0456 | D745: Delhi | E745: Beauty | F745: Shampoo | G745: 4 | H745: 3873.18 | I745: 0.2 | J745: 12394.18 | K745: 10444.83 | L745: 1949.35 | M745: Store | N745: Wallet | O745: No
A746: R00745 | B746: 45835 | C746: C0226 | D746: Pune | E746: Fashion | F746: Jacket | G746: 2 | H746: 794.41 | I746: 0 | J746: 1588.82 | K746: 1192.76 | L746: 396.06 | M746: Store | N746: Card | O746: No
A747: R00746 | B747: 46027 | C747: C0167 | D747: Gurugram | E747: Electronics | F747: Headphones | G747: 3 | H747: 481.3 | I747: 0 | J747: 1443.9 | K747: 1209.56 | L747: 234.34 | M747: Online | N747: Card | O747: No
A748: R00747 | B748: 45838 | C748: C0211 | D748: gurugram | E748: Home | F748: Lamp | G748: 4 | H748: 1997.44 | I748: 0.1 | J748: 7190.78 | K748: 4566.91 | L748: 2623.87 | M748: Online | N748: UPI | O748: No
A749: R00748 | B749: 46152 | C749: C0192 | D749: Chennai | E749: Beauty | F749: Serum | G749: 6 | H749: 512.68 | I749: 0.05 | J749: 2922.28 | K749: 2241.25 | L749: 681.03 | M749: Store | N749: Wallet | O749: No
A750: R00749 | B750: 45843 | C750: C0171 | D750: Jaipur | E750: Fashion | F750: Shoes | G750: 5 | H750: 3116.39 | I750: 0.1 | J750: 14023.75 | K750: 10164.88 | L750: 3858.87 | M750: Online | N750: UPI | O750: No
... A756: R00755 | B756: 46147 | C756: C0307 | D756: Noida | E756: Electronics | F756: Mouse | G756: 6 | H756: 380.6 | I756: 0.1 | J756: 2055.24 | K756: 1366.73 | L756: 688.51 | M756: Online | N756: Cash | O756: No
A757: R00756 | B757: 45996 | C757: C0275 | E757: Fashion | F757: Jeans | G757: 4 | H757: 272.55 | I757: 0 | J757: 1090.2 | K757: 877.37 | L757: 212.83 | M757: Store | N757: Wallet | O757: Yes
A758: R00757 | B758: 46083 | C758: C0235 | D758: Hyderabad | E758: Electronics | F758: Keyboard | G758: 6 | H758: 4789.75 | I758: 0.05 | J758: 27301.57 | K758: 15913.97 | L758: 11387.6 | M758: Store | N758: Card | O758: Yes
A759: R00758 | B759: 46162 | C759: C0299 | D759: Chennai | E759: Beauty | F759: Serum | G759: 6 | H759: 458.64 | I759: 0.2 | J759: 2201.47 | K759: 1755.44 | L759: 446.03 | M759: Online | N759: Cash | O759: Yes
A760: R00759 | B760: 45823 | C760: C0175 | D760: Bengaluru | E760: Fashion | F760: T-Shirt | G760: 1 | H760: 2025.17 | I760: 0 | J760: 2025.17 | K760: 1145.19 | L760: 879.98 | M760: Store | N760: Wallet | O760: No
A761: R00760 | B761: 46209 | C761: C0276 | D761: Pune | E761: Home | F761: Cookware | G761: 2 | H761: 3930.81 | I761: 0.15 | J761: 6682.38 | K761: 5066.75 | L761: 1615.63 | M761: Online | N761: Card | O761: No
A762: R00761 | B762: 45813 | C762: C0509 | D762: Bengaluru | E762: Beauty | F762: Sunscreen | G762: 4 | H762: 755.1 | I762: 0.05 | J762: 2869.38 | K762: 2010.91 | L762: 858.47 | M762: Store | N762: UPI | O762: Yes
A763: R00762 | B763: 46204 | C763: C0390 | D763: Pune | E763: Home | F763: Cookware | G763: 6 | H763: 488.23 | I763: 0.1 | J763: 2636.44 | K763: 1821.44 | L763: 815 | M763: Online | N763: Card | O763: No
A764: R00763 | B764: 46135 | C764: C0347 | D764: Jaipur | E764: Electronics | F764: Headphones | G764: 2 | H764: 2775.19 | I764: 0.1 | J764: 4995.34 | K764: 3567.22 | L764: 1428.12 | M764: Online | N764: Wallet | O764: Yes
A765: R00764 | B765: 45906 | C765: C0451 | D765: Kolkata | E765: Home | F765: Lamp | G765: 6 | H765: 1123.08 | I765: 0.1 | J765: 6064.63 | K765: 3793.15 | L765: 2271.48 | M765: Store | N765: Cash | O765: Yes
A766: R00765 | B766: 45867 | C766: C0309 | D766: Bengaluru | E766: Beauty | F766: Shampoo | G766: 6 | H766: 852.56 | I766: 0.05 | J766: 4859.59 | K766: 3002.34 | L766: 1857.25 | M766: Store | N766: UPI | O766: No
A767: R00766 | B767: 46176 | C767: C0289 | D767: Kolkata | E767: Beauty | F767: Sunscreen | G767: 3 | H767: 4866.46 | I767: 0.05 | J767: 13869.41 | K767: 9344.1 | L767: 4525.31 | M767: Online | N767: Wallet | O767: No
A768: R00767 | B768: 45774 | C768: C0140 | D768: Hyderabad | E768: Fashion | F768: Jeans | G768: 6 | H768: 3146.94 | I768: 0.15 | J768: 16049.39 | K768: 11788.29 | L768: 4261.1 | M768: Online | N768: UPI | O768: No
A769: R00768 | B769: 45664 | C769: C0405 | D769: Jaipur | E769: Home | F769: Cookware | G769: 1 | H769: 2018.16 | I769: 0.1 | J769: 1816.34 | K769: 1210.4 | L769: 605.94 | M769: Online | N769: Wallet | O769: No
... A882: R00881 | B882: 45913 | C882: C0061 | D882: Pune | E882: Fashion | F882: Backpack | G882: 5 | H882: 4922.77 | I882: 0.2 | J882: 19691.08 | K882: 12168.84 | L882: 7522.24 | M882: Store | N882: Cash | O882: Yes
A883: R00882 | B883: 45732 | C883: C0025 | E883: Home | F883: Mixer | G883: 5 | H883: 3538.49 | I883: 0.1 | J883: 15923.2 | K883: 12562.07 | L883: 3361.13 | M883: Online | N883: Cash | O883: No
A884: R00883 | B884: 45744 | C884: C0136 | D884: Hyderabad | E884: Home | F884: Bedsheet | G884: 2 | H884: 3353.48 | I884: 0.1 | J884: 6036.26 | K884: 4822.62 | L884: 1213.64 | M884: Store | N884: UPI | O884: Yes
A885: R00884 | B885: 45924 | C885: C0408 | D885: delhi | E885: Fashion | F885: Shoes | G885: 2 | H885: 441.13 | I885: 0 | J885: 882.26 | K885: 552.37 | L885: 329.89 | M885: Store | N885: Wallet | O885: Yes
A886: R00885 | B886: 46055 | C886: C0075 | D886: Jaipur | E886: Electronics | F886: Headphones | G886: 1 | H886: 4651.05 | I886: 0.15 | J886: 3953.39 | K886: 3007.69 | L886: 945.7 | M886: Online | N886: Wallet | O886: No
A887: R00886 | B887: 45783 | C887: C0447 | D887: Noida | E887: Beauty | F887: Shampoo | G887: 6 | H887: 5012.01 | I887: 0 | J887: 30072.06 | K887: 22701.78 | L887: 7370.28 | M887: Store | N887: Wallet | O887: No
A888: R00887 | B888: 46101 | C888: C0497 | D888: Hyderabad | E888: Fashion | F888: Jeans | G888: 2 | H888: 1709.12 | I888: 0.15 | J888: 2905.5 | K888: 1699.1 | L888: 1206.4 | M888: Store | N888: UPI | O888: No
A889: R00888 | B889: 45909 | C889: C0308 | D889: Noida | E889: Fashion | F889: Jacket | G889: 5 | H889: 4604.89 | I889: 0 | J889: 23024.45 | K889: 13852.36 | L889: 9172.09 | M889: Store | N889: Cash | O889: Yes
A890: R00889 | B890: 45673 | C890: C0344 | D890: Noida | E890: Electronics | F890: Smartwatch | G890: 6 | H890: 2086.54 | I890: 0.05 | J890: 11893.28 | K890: 9349.14 | L890: 2544.14 | M890: Online | N890: Wallet | O890: No
A891: R00890 | B891: 45773 | C891: C0430 | D891: Chennai | E891: Fashion | F891: T-Shirt | G891: 3 | H891: 4858.96 | I891: 0 | J891: 14576.88 | K891: 11478.96 | L891: 3097.92 | M891: Online | N891: Card | O891: No
A892: R00891 | B892: 45691 | C892: C0210 | D892: gurugram | E892: Home | F892: Cookware | G892: 5 | H892: 534.26 | I892: 0.1 | J892: 2404.17 | K892: 1640.53 | L892: 763.64 | M892: Online | N892: Wallet | O892: Yes
A893: R00892 | B893: 46086 | C893: C0133 | D893: Mumbai | E893: Beauty | F893: Face Wash | G893: 5 | H893: 1101.92 | I893: 0 | J893: 5509.6 | K893: 3276.67 | L893: 2232.93 | M893: Online | N893: Card | O893: No
A894: R00893 | B894: 45747 | C894: C0125 | D894: Chennai | E894: Fashion | F894: Jeans | G894: 6 | H894: 3643.34 | I894: 0.2 | J894: 17488.03 | K894: 10881.61 | L894: 6606.42 | M894: Store | N894: Wallet | O894: Yes
A895: R00894 | B895: 45708 | C895: C0233 | D895: Jaipur | E895: Electronics | F895: Power Bank | G895: 3 | H895: 3547.24 | I895: 0.2 | J895: 8513.38 | K895: 4957.01 | L895: 3556.37 | M895: Store | N895: UPI | O895: Yes
... A1195: R01194 | B1195: 46232 | C1195: C0295 | D1195: Gurugram | E1195: Beauty | F1195: Perfume | G1195: 1 | H1195: 2681.19 | I1195: 0.2 | J1195: 2144.95 | K1195: 1778.01 | L1195: 366.94 | M1195: Online | N1195: Wallet | O1195: Yes
A1196: R01195 | B1196: 46159 | C1196: C0288 | E1196: Beauty | F1196: Face Wash | G1196: 4 | H1196: 5156.73 | I1196: 0.05 | J1196: 19595.57 | K1196: 14879.11 | L1196: 4716.46 | M1196: Store | N1196: UPI | O1196: No
A1197: R01196 | B1197: 46096 | C1197: C0134 | D1197: Delhi | E1197: Electronics | F1197: Keyboard | G1197: 5 | H1197: 2580.52 | I1197: 0 | J1197: 12902.6 | K1197: 10896.2 | L1197: 2006.4 | M1197: Online | N1197: UPI | O1197: Yes
A1198: R01197 | B1198: 46144 | C1198: C0245 | D1198: Delhi | E1198: Fashion | F1198: Jeans | G1198: 3 | H1198: 1746.82 | I1198: 0 | J1198: 5240.46 | K1198: 3893.96 | L1198: 1346.5 | M1198: Online | N1198: Wallet | O1198: Yes
A1199: R01198 | B1199: 45856 | C1199: C0251 | D1199: Delhi | E1199: Beauty | F1199: Face Wash | G1199: 3 | H1199: 456.92 | I1199: 0.2 | J1199: 1096.61 | K1199: 812.99 | L1199: 283.62 | M1199: Store | N1199: Wallet | O1199: No
A1200: R01199 | B1200: 45963 | C1200: C0326 | D1200: Noida | E1200: Beauty | F1200: Perfume | G1200: 2 | H1200: 3361.76 | I1200: 0 | J1200: 6723.52 | K1200: 5676.17 | L1200: 1047.35 | M1200: Store | N1200: Wallet | O1200: No
A1201: R01200 | B1201: 46026 | C1201: C0188 | D1201: Mumbai | E1201: Beauty | F1201: Serum | G1201: 2 | H1201: 1300.65 | I1201: 0 | J1201: 2601.3 | K1201: 2070.52 | L1201: 530.78 | M1201: Store | N1201: UPI | O1201: No
A1202: R00026 | B1202: 45760 | C1202: C0317 | D1202: Kolkata | E1202: Electronics | F1202: Headphones | G1202: 6 | H1202: 3579.33 | I1202: 0 | J1202: 21475.98 | K1202: 15043.22 | L1202: 6432.76 | M1202: Online | N1202: Wallet | O1202: No
A1203: R00200 | B1203: 46213 | C1203: C0038 | D1203: Pune | E1203: Home | F1203: Mixer | G1203: 3 | H1203: 4084.56 | I1203: 0.1 | J1203: 11028.31 | K1203: 8133.67 | L1203: 2894.64 | M1203: Store | N1203: UPI | O1203: No
A1204: R00400 | B1204: 46245 | C1204: C0461 | D1204: Delhi | E1204: Home | F1204: Bottle | G1204: 6 | H1204: 4323.59 | I1204: 0.1 | J1204: 23347.39 | K1204: 19017.59 | L1204: 4329.8 | M1204: Online | N1204: Card | O1204: No
A1205: R00651 | B1205: 45818 | C1205: C0204 | D1205: Bengaluru | E1205: Fashion | F1205: T-Shirt | G1205: 6 | H1205: 5039.68 | I1205: 0.15 | J1205: 25702.37 | K1205: 21201.24 | L1205: 4501.13 | M1205: Store | N1205: UPI | O1205: No
A1206: R00991 | B1206: 46101 | C1206: C0259 | D1206: Chennai | E1206: Home | F1206: Mixer | G1206: 4 | H1206: 1977.42 | I1206: 0.1 | J1206: 7118.71 | K1206: 5574.67 | L1206: 1544.04 | M1206: Store | N1206: UPI | O1206: No

Sheet Clean_Data
A1: Order_ID | B1: Order_Date | C1: Customer_ID | D1: City | E1: Category | F1: Product | G1: Quantity | H1: Unit_Price | I1: Discount_Pct | J1: Sales | K1: Cost | L1: Profit | M1: Channel | N1: Payment_Mode | O1: Returned | P1: Order_Month | Q1: Order_Year | R1: Profit_Margin
A2: R01111 | B2: 46103 | C2: C0163 | D2: Noida | E2: Beauty | F2: Shampoo | G2: 4 | H2: 156.2 | I2: 0.15 | J2: 531.08 | K2: 414.3 | L2: 116.78 | M2: Store | N2: Cash | O2: Yes | P2: =TEXT(B2,"mmm") -> Mar | Q2: =YEAR(B2) -> 2026 | R2: =IFERROR(L2/J2,0) -> 0.21989154
A3: R00571 | B3: 45697 | C3: C0146 | D3: Gurugram | E3: Beauty | F3: Face Wash | G3: 6 | H3: 156.94 | I3: 0.1 | J3: 847.48 | K3: 584.29 | L3: 263.19 | M3: Store | N3: Card | O3: Yes | P3: =TEXT(B3,"mmm") -> Feb | Q3: =YEAR(B3) -> 2025 | R3: =IFERROR(L3/J3,0) -> 0.310556
A4: R00864 | B4: 46210 | C4: C0428 | D4: Delhi | E4: Fashion | F4: T-Shirt | G4: 5 | H4: 157.92 | I4: 0.15 | J4: 671.16 | K4: 561.68 | L4: 109.48 | M4: Online | N4: Wallet | O4: No | P4: =TEXT(B4,"mmm") -> Jul | Q4: =YEAR(B4) -> 2026 | R4: =IFERROR(L4/J4,0) -> 0.16312057
A5: R00532 | B5: 45985 | C5: C0355 | D5: Delhi | E5: Home | F5: Bedsheet | G5: 5 | H5: 165.05 | I5: 0.15 | J5: 701.46 | K5: 590.43 | L5: 111.03 | M5: Online | N5: Cash | O5: Yes | P5: =TEXT(B5,"mmm") -> Nov | Q5: =YEAR(B5) -> 2025 | R5: =IFERROR(L5/J5,0) -> 0.15828415
A6: R00787 | B6: 45727 | C6: C0205 | D6: Kolkata | E6: Electronics | F6: Smartwatch | G6: 6 | H6: 167.23 | I6: 0.05 | J6: 953.21 | K6: 557.44 | L6: 395.77 | M6: Online | N6: Cash | O6: No | P6: =TEXT(B6,"mmm") -> Mar | Q6: =YEAR(B6) -> 2025 | R6: =IFERROR(L6/J6,0) -> 0.41519707
A7: R00222 | B7: 45922 | C7: C0216 | D7: Bengaluru | E7: Electronics | F7: Smartwatch | G7: 2 | H7: 175.25 | I7: 0.15 | J7: 297.93 | K7: 193.54 | L7: 104.39 | M7: Store | N7: Cash | O7: No | P7: =TEXT(B7,"mmm") -> Sep | Q7: =YEAR(B7) -> 2025 | R7: =IFERROR(L7/J7,0) -> 0.35038432
A8: R01134 | B8: 45690 | C8: C0380 | D8: Pune | E8: Home | F8: Bedsheet | G8: 3 | H8: 184.76 | I8: 0 | J8: 554.28 | K8: 450.91 | L8: 103.37 | M8: Online | N8: UPI | O8: No | P8: =TEXT(B8,"mmm") -> Feb | Q8: =YEAR(B8) -> 2025 | R8: =IFERROR(L8/J8,0) -> 0.18649419
A9: R00147 | B9: 46226 | C9: C0339 | D9: Hyderabad | E9: Electronics | F9: Headphones | G9: 2 | H9: 187.29 | I9: 0 | J9: 374.58 | K9: 283.88 | L9: 90.7 | M9: Store | N9: UPI | O9: No | P9: =TEXT(B9,"mmm") -> Jul | Q9: =YEAR(B9) -> 2026 | R9: =IFERROR(L9/J9,0) -> 0.24213786
A10: R00582 | B10: 46144 | C10: C0175 | D10: Delhi | E10: Electronics | F10: Mouse | G10: 3 | H10: 187.54 | I10: 0 | J10: 562.62 | K10: 316.25 | L10: 246.37 | M10: Online | N10: Cash | O10: No | P10: =TEXT(B10,"mmm") -> May | Q10: =YEAR(B10) -> 2026 | R10: =IFERROR(L10/J10,0) -> 0.43789769
A11: R00740 | B11: 46081 | C11: C0128 | D11: Mumbai | E11: Fashion | F11: Jeans | G11: 6 | H11: 199.23 | I11: 0.15 | J11: 1016.07 | K11: 636.88 | L11: 379.19 | M11: Online | N11: Wallet | O11: Yes | P11: =TEXT(B11,"mmm") -> Feb | Q11: =YEAR(B11) -> 2026 | R11: =IFERROR(L11/J11,0) -> 0.37319279
A12: R00063 | B12: 46257 | C12: C0348 | D12: Kolkata | E12: Electronics | F12: Keyboard | G12: 5 | H12: 207.01 | I12: 0 | J12: 1035.05 | K12: 638.48 | L12: 396.57 | M12: Online | N12: Cash | O12: No | P12: =TEXT(B12,"mmm") -> Aug | Q12: =YEAR(B12) -> 2026 | R12: =IFERROR(L12/J12,0) -> 0.38314091
A13: R00818 | B13: 45964 | C13: C0446 | D13: Noida | E13: Beauty | F13: Perfume | G13: 6 | H13: 207.01 | I13: 0 | J13: 1242.06 | K13: 715 | L13: 527.06 | M13: Store | N13: UPI | O13: No | P13: =TEXT(B13,"mmm") -> Nov | Q13: =YEAR(B13) -> 2025 | R13: =IFERROR(L13/J13,0) -> 0.42434343
... A1201: R00416 | B1201: 45843 | C1201: C0248 | D1201: Chennai | E1201: Beauty | F1201: Perfume | G1201: 3 | H1201: 5487.44 | I1201: 0.15 | J1201: 13992.97 | K1201: 8709.8 | L1201: 5283.17 | M1201: Store | N1201: Card | O1201: No | P1201: =TEXT(B1201,"mmm") -> Jul | Q1201: =YEAR(B1201) -> 2025 | R1201: =IFERROR(L1201/J1201,0) -> 0.37755887

Sheet Analysis
A1: KPI | B1: Value | C1: .
A2: Total Sales | B2: =SUM(Clean_Data!J:J) -> 10926608
A3: Total Orders | B3: =COUNTA(Clean_Data!A:A)-1 -> 1200
A4: Average Order Value | B4: =B2/B3 -> 9105.5069
A5: Total Customers | B5: =COUNTA(_xlfn.UNIQUE(Clean_Data!C2:C1201)) -> 478
A6: Total Quantity | B6: =SUM(Clean_Data!G:G) -> 4252
A7: Total Profit | B7: =SUM(Clean_Data!L:L) -> 3275893.4
A8: Profit Margin | B8: =B7/B2 -> 0.2998088
A9: Top Category by Sales | B9: Fashion | C9: 2936782.6
A10: Top Product by Sales | B10: Backpack | C10: ₹705,219.66
A11: Top City by Sales | B11: Mumbai | C11: 1329580.6
A12: Top Category by Profit | B12: Backpack | C12: ₹875,025.58
A13: Top Sales Channel | B13: Online | C13: 5638053.1
A14: Returned Orders | B14: 317
A15: Return Rate | B15: =317/1200 -> 0.26416667
A16: Top Customer by Sales | B16: C0240 | C16: ₹90,247.39
A17: Top Payment Mode | B17: Card | C17: 2830682.4
A18: Top Sales Year | B18: 2025 | C18: 6769664.2
A20: Business Insights & Recommendations
A22: Insight 1 — Fashion is the strongest category
A23: Actual Observation: Fashion generated the highest sales of ₹2,936,782.56 and the highest profit of ₹875,025.58.
A24: Business Meaning: Fashion is the strongest category in both revenue and profitability.
A25: Recommendation: Maintain strong inventory for Fashion products and use targeted promotions on its best-selling items.
A27: Insight 2 — Backpack is the top-selling product
A28: Actual Observation: Backpack generated the highest product sales of ₹705,219.66.
A29: Business Meaning: Backpack is currently the strongest individual product by revenue.
A30: Recommendation: Ensure sufficient stock availability and consider using Backpack in promotional campaigns or product bundles.
A32: Insight 3 — Online channel performs slightly better than Store
A33: Actual Observation: Online sales were ₹5,638,053.06, compared with Store sales of ₹5,288,555.27.
A34: Business Meaning: Online contributes slightly more revenue than physical Store sales.
... A45: Recommendation: Prioritize inventory availability and targeted marketing in Mumbai while studying successful patterns that can be applied to other cities.

Sheet Pivot_Tables
A1: Sales by Category | D1: Sales by Product | G1: Sales by City | J1: Monthly Sales Trend | M1: Profit by Category | P1: Sales by Channel | S1: Returned Orders Analysis | V1: Top Customers by Sales | Y1: Sales by Payment Mode | AB1: Sales by Year
A2: Category | B2: Sum of Sales | D2: Product | E2: Sum of Sales | G2: City | H2: Sum of Sales | J2: Order_Month | K2: Sum of Sales | M2: Category | N2: Sum of Profit | P2: Channel | Q2: Sum of Sales | S2: Returned | T2: Count of Order_ID | V2: Customer_ID | W2: Sum of Sales | Y2: Payment_Mode | Z2: Sum of Sales | AB2: Order_Year | AC2: Sum of Sales
A3: Fashion | B3: 2936782.6 | D3: Backpack | E3: 705219.66 | G3: Mumbai | H3: 1329580.6 | J3: Jan | K3: 1245910.9 | M3: Fashion | N3: 875025.58 | P3: Online | Q3: 5638053.1 | S3: No | T3: 883 | V3: C0240 | W3: 90247.39 | Y3: Card | Z3: 2830682.4 | AB3: 2025 | AC3: 6769664.2
A4: Home | B4: 2743282.3 | D4: Mixer | E4: 656808.32 | G4: Chennai | H4: 1220391.5 | J4: Feb | K4: 1085011 | M4: Electronics | N4: 834892.71 | P4: Store | Q4: 5288555.3 | S4: Yes | T4: 317 | V4: C0430 | W4: 83457.09 | Y4: UPI | Z4: 2779600 | AB4: 2026 | AC4: 4156944.1
A5: Electronics | B5: 2701550.7 | D5: Jacket | E5: 638609.82 | G5: Bengaluru | H5: 1173305.8 | J5: Mar | K5: 1006006.3 | M5: Home | N5: 809342.13 | P5: Grand Total | Q5: 10926608 | S5: Grand Total | T5: 1200 | V5: C0164 | W5: 80973.28 | Y5: Cash | Z5: 2772913.4 | AB5: Grand Total | AC5: 10926608
A6: Beauty | B6: 2544992.7 | D6: Jeans | E6: 630847.47 | G6: Hyderabad | H6: 1172164.8 | J6: Apr | K6: 1186986.6 | M6: Beauty | N6: 756632.95 | V6: C0468 | W6: 80446.41 | Y6: Wallet | Z6: 2543412.5
A7: Grand Total | B7: 10926608 | D7: Power Bank | E7: 599169.71 | G7: Noida | H7: 1147705.2 | J7: May | K7: 1043253.7 | M7: Grand Total | N7: 3275893.4 | V7: C0500 | W7: 74292.35 | Y7: Grand Total | Z7: 10926608
D8: Shampoo | E8: 597672.58 | G8: Pune | H8: 1109660.1 | J8: Jun | K8: 950508.13 | V8: C0277 | W8: 72484.28
D9: Bottle | E9: 592239.68 | G9: Delhi | H9: 1105537.6 | J9: Jul | K9: 1334992.4 | V9: C0332 | W9: 72260.32
D10: Headphones | E10: 587953.34 | G10: Jaipur | H10: 957209.65 | J10: Aug | K10: 923326.75 | V10: C0172 | W10: 71782.99
D11: Cookware | E11: 584478.12 | G11: Kolkata | H11: 859738.53 | J11: Sep | K11: 663415.58 | V11: C0318 | W11: 71367.71
D12: Keyboard | E12: 567153.21 | G12: Gurugram | H12: 800449.42 | J12: Oct | K12: 435920.88 | V12: C0310 | W12: 70489.44
D13: Grand Total | E13: 6160151.9 | G13: Unknown | H13: 50865.14 | J13: Nov | K13: 564496.56 | V13: C0147 | W13: 64828.12
G14: Grand Total | H14: 10926608 | J14: Dec | K14: 486779.57 | V14: C0392 | W14: 62010
J15: Grand Total | K15: 10926608 | V15: C0027 | W15: 61764.12
V16: C0197 | W16: 61309.05
V17: C0070 | W17: 60889.03
V18: C0118 | W18: 60825.25
V19: C0322 | W19: 59951.41
V20: C0261 | W20: 59325.19
V21: C0153 | W21: 57841.77
V22: C0427 | W22: 57520.45
V23: C0336 | W23: 56911.23
V24: C0303 | W24: 53944.85
V25: C0471 | W25: 53490.99
V26: C0325 | W26: 52722.34
V27: C0129 | W27: 52595.09
... V481: Grand Total | W481: 10926608

Sheet Dashboard
A1: Retail Sales Analysis Dashboard
A4: Total Sales | D4: Total Orders | G4: Average Order Value | J4: Total Profit | M4: Profit Margin
A7: =Analysis!B2 -> 10926608 | D7: =Analysis!B3 -> 1200 | G7: =Analysis!B4 -> 9105.5069 | J7: =Analysis!B7 -> 3275893.4 | M7: =Analysis!B8 -> 0.2998088
